README.txt
setup.py
grun/__init__.py
grun.egg-info/PKG-INFO
grun.egg-info/SOURCES.txt
grun.egg-info/dependency_links.txt
grun.egg-info/top_level.txt
grun/gui/__init__.py
grun/gui/gtkgrun.py
grun/gui/tkgrun.py
test/test_clipboard.py
test/test_complex.py
test/test_conf.py
test/test_dialog.py
test/test_form.py
test/test_grun_decorator.py
test/test_grunapp.py
test/test_iconapp.py
test/test_notify.py
test/test_popapp.py
test/test_progress.py
test/test_types.py