Metadata-Version: 1.0
Name: grun
Version: 0.14
Summary: The simplest GUI builder (tk/gtk), for RAD scripts
Home-page: http://www.manatlan.com/page/grun
Author: manatlan
Author-email: manatlan@gmail.com
License: MIT
Platform: UNKNOWN
Classifier: Development Status :: 4 - Beta
Classifier: Environment :: X11 Applications :: GTK
Classifier: Environment :: Win32 (MS Windows)
Classifier: Environment :: MacOS X
Classifier: Intended Audience :: Developers
Classifier: License :: OSI Approved :: MIT License
Classifier: Operating System :: OS Independent
Classifier: Programming Language :: Python
Classifier: Topic :: Software Development :: Libraries :: Python Modules
Classifier: Topic :: Utilities
